iautomate/__init__.py
iautomate/__main__.py
iautomate/__version__.py
iautomate/abstract_resource.py
iautomate/directory.py
iautomate/directory_resource.py
iautomate/execution.py
iautomate/execution_resource.py
iautomate/file.py
iautomate/file_resource.py
iautomate/global_variables.py
iautomate/iautomate.py
iautomate/package.py
iautomate/package_helper.py
iautomate/package_resource.py
iautomate/service.py
iautomate/service_resource.py
iautomate/shell_helper.py
iautomate/string_helper.py
iautomate/helpers/__init__.py
iautomate/helpers/package_helper.py
iautomate/helpers/shell_helper.py
iautomate/helpers/string_helper.py
iautomate/resources/__init__.py
iautomate/resources/abstract_resource.py
iautomate/resources/directory_resource.py
iautomate/resources/execution_resource.py
iautomate/resources/file_resource.py
iautomate/resources/package_resource.py
iautomate/resources/service_resource.py
iautomate-0.36.dist-info/METADATA
iautomate-0.36.dist-info/RECORD
iautomate-0.36.dist-info/WHEEL
iautomate-0.36.dist-info/entry_points.txt
iautomate-0.36.dist-info/top_level.txt
